odoo/addons/mrp_mass_production_order/README.rst
odoo/addons/mrp_mass_production_order/__init__.py
odoo/addons/mrp_mass_production_order/__manifest__.py
odoo/addons/mrp_mass_production_order/i18n/ca.po
odoo/addons/mrp_mass_production_order/i18n/es.po
odoo/addons/mrp_mass_production_order/i18n/it.po
odoo/addons/mrp_mass_production_order/i18n/mrp_mass_production_order.pot
odoo/addons/mrp_mass_production_order/i18n/pt_BR.po
odoo/addons/mrp_mass_production_order/readme/CONTRIBUTORS.md
odoo/addons/mrp_mass_production_order/readme/DESCRIPTION.md
odoo/addons/mrp_mass_production_order/readme/USAGE.md
odoo/addons/mrp_mass_production_order/security/ir.model.access.csv
odoo/addons/mrp_mass_production_order/static/description/icon.png
odoo/addons/mrp_mass_production_order/static/description/icon.svg
odoo/addons/mrp_mass_production_order/static/description/index.html
odoo/addons/mrp_mass_production_order/tests/__init__.py
odoo/addons/mrp_mass_production_order/tests/test_mrp_mass_production_order.py
odoo/addons/mrp_mass_production_order/wizards/__init__.py
odoo/addons/mrp_mass_production_order/wizards/mrp_mass_order_wizard.py
odoo/addons/mrp_mass_production_order/wizards/mrp_mass_order_wizard.xml
odoo_addon_mrp_mass_production_order-18.0.1.0.0.3.dist-info/METADATA
odoo_addon_mrp_mass_production_order-18.0.1.0.0.3.dist-info/WHEEL
odoo_addon_mrp_mass_production_order-18.0.1.0.0.3.dist-info/top_level.txt
odoo_addon_mrp_mass_production_order-18.0.1.0.0.3.dist-info/RECORD
