Metadata-Version: 2.1
Name: odoo-addon-mrp_mass_production_order
Version: 18.0.1.0.0.3
Requires-Python: >=3.10
Requires-Dist: odoo-addon-mrp_tag==18.0.*
Requires-Dist: odoo==18.0.*
Summary: Create multiple manufacturing orders in one step
Home-page: https://github.com/OCA/manufacture
License: AGPL-3
Author: Antoni Marroig, APSL-Nagarro, Odoo Community Association (OCA)
Author-email: support@odoo-community.org
Classifier: Programming Language :: Python
Classifier: Framework :: Odoo
Classifier: Framework :: Odoo :: 18.0
Classifier: License :: OSI Approved :: GNU Affero General Public License v3
